aqipy/__init__.py
aqipy/__main__.py
aqipy-0.2.1.dist-info/LICENSE
aqipy-0.2.1.dist-info/METADATA
aqipy-0.2.1.dist-info/WHEEL
aqipy-0.2.1.dist-info/entry_points.txt
aqipy-0.2.1.dist-info/top_level.txt
aqipy-0.2.1.dist-info/RECORD
