Metadata-Version: 2.1
Name: aqipy
Version: 0.2.1
Summary: A simple CLI to get live Air Quality Indices
Home-page: https://github.com/danoscarmike/aqipy
Author: Dan O'Meara
Author-email: omeara.dan@gmail.com
License: UNKNOWN
Platform: UNKNOWN
Classifier: Programming Language :: Python :: 3
Classifier: Development Status :: 1 - Planning
Classifier: License :: OSI Approved :: MIT License
Requires-Dist: click
Requires-Dist: requests
